crimson_solana_toolkit/__init__.py
crimson_solana_toolkit/agent.py
crimson_solana_toolkit/programs.py
crimson_solana_toolkit/tools.py
crimson_solana_toolkit-0.1.0.dist-info/METADATA
crimson_solana_toolkit-0.1.0.dist-info/WHEEL
crimson_solana_toolkit-0.1.0.dist-info/entry_points.txt
crimson_solana_toolkit-0.1.0.dist-info/top_level.txt
crimson_solana_toolkit-0.1.0.dist-info/RECORD
