Metadata-Version: 2.2
Name: crimson-solana-toolkit
Version: 0.1.0
Summary: A comprehensive Solana blockchain toolkit for the Crimson Labs ecosystem.
Home-page: https://github.com/crimson-labs/crimson-solana-toolkit
Author: Crimson Labs
Author-email: crimsonlabsai@gmail.com
Project-URL: Source, https://github.com/crimson-labs/crimson-solana-toolkit
Project-URL: Tracker, https://github.com/crimson-labs/crimson-solana-toolkit/issues
Classifier: Development Status :: 3 - Alpha
Classifier: Intended Audience :: Developers
Classifier: License :: OSI Approved :: MIT License
Classifier: Programming Language :: Python :: 3.8
Classifier: Programming Language :: Python :: 3.9
Classifier: Programming Language :: Python :: 3.10
Classifier: Topic :: Software Development :: Libraries :: Python Modules
Classifier: Topic :: Software Development :: Libraries :: Application Frameworks
Classifier: Topic :: Scientific/Engineering :: Artificial Intelligence
Classifier: Topic :: Software Development :: Libraries :: Python Modules
Classifier: Topic :: System :: Distributed Computing
Classifier: Topic :: Office/Business :: Financial
Classifier: Topic :: Security :: Cryptography
Requires-Python: >=3.8
Requires-Dist: solana
Requires-Dist: anchorpy
Requires-Dist: base58
Requires-Dist: construct
Requires-Dist: pytest
Requires-Dist: pytest-asyncio
Requires-Dist: crimson-agent
Requires-Dist: pandas
Requires-Dist: numpy
Requires-Dist: networkx
Requires-Dist: plotly
Requires-Dist: scipy
Requires-Dist: matplotlib
Requires-Dist: seaborn
Provides-Extra: dev
Requires-Dist: pytest; extra == "dev"
Requires-Dist: pytest-asyncio; extra == "dev"
Requires-Dist: pytest-cov; extra == "dev"
Requires-Dist: black; extra == "dev"
Requires-Dist: isort; extra == "dev"
Requires-Dist: mypy; extra == "dev"
Requires-Dist: flake8; extra == "dev"
Requires-Dist: sphinx; extra == "dev"
Requires-Dist: sphinx-rtd-theme; extra == "dev"
Provides-Extra: docs
Requires-Dist: sphinx; extra == "docs"
Requires-Dist: sphinx-rtd-theme; extra == "docs"
Requires-Dist: sphinx-autodoc-typehints; extra == "docs"
Dynamic: author
Dynamic: author-email
Dynamic: classifier
Dynamic: description
Dynamic: description-content-type
Dynamic: home-page
Dynamic: project-url
Dynamic: provides-extra
Dynamic: requires-dist
Dynamic: requires-python
Dynamic: summary
